{"Graph":[[{"TargetIndex":1,"Direction":1},{"TargetIndex":2,"Direction":1},{"TargetIndex":3,"Direction":1}],[{"TargetIndex":0,"Direction":-1}],[{"TargetIndex":0,"Direction":-1}],[{"TargetIndex":0,"Direction":-1}]],"NodeIdToIndex":{"aRp_xALtqllVSohNh":0,"67b22c740f67a3dbf64ce25a":1,"aZQjPq4RYF_aDZ63r":2,"aKwNXQRtshPjGeYSw":3},"IndexToNodeData":[{"NodeId":"aRp_xALtqllVSohNh","Type":"Application"},{"NodeId":"67b22c740f67a3dbf64ce25a","Type":"Report"},{"NodeId":"aZQjPq4RYF_aDZ63r","Type":"Workflow"},{"NodeId":"aKwNXQRtshPjGeYSw","Type":"Workspace"}]}