{"Graph":[[{"TargetIndex":1,"Direction":1},{"TargetIndex":2,"Direction":1},{"TargetIndex":3,"Direction":1}],[{"TargetIndex":0,"Direction":-1}],[{"TargetIndex":0,"Direction":-1}],[{"TargetIndex":0,"Direction":-1}]],"NodeIdToIndex":{"aDXj1MnwNR32UmSsD":0,"67c59563ff2b88a40ee4bf2d":1,"aIKS7GDXhLC2pPYuw":2,"aLmKnFV1Tdu7ZtpPp":3},"IndexToNodeData":[{"NodeId":"aDXj1MnwNR32UmSsD","Type":"Application"},{"NodeId":"67c59563ff2b88a40ee4bf2d","Type":"Report"},{"NodeId":"aIKS7GDXhLC2pPYuw","Type":"Workflow"},{"NodeId":"aLmKnFV1Tdu7ZtpPp","Type":"Workspace"}]}