{
  "description": "This is Test Description",
  "acronym": "QAEE",
  "trackingFieldId": "67b22c740f67a3dbf64ce258",
  "layout": [
    {
      "fieldId": "amfso",
      "helpTextType": "None",
      "helpText": " ",
      "layoutType": "Field",
      "id": "67b22c79ab5c1dc8cb47055e",
      "row": 1,
      "col": 1,
      "sizex": 4,
      "sizey": 0
    },
    {
      "fieldId": "ao4wj",
      "helpTextType": "None",
      "helpText": " ",
      "layoutType": "Field",
      "id": "67b22c791a3312fc960d0b07",
      "row": 1,
      "col": 2,
      "sizex": 4,
      "sizey": 0
    },
    {
      "fieldId": "af61v",
      "helpTextType": "None",
      "helpText": " ",
      "layoutType": "Field",
      "id": "67b22c79b5af268ac1ec12ae",
      "row": 1,
      "col": 4,
      "sizex": 4,
      "sizey": 0
    },
    {
      "fieldId": "aejjf",
      "helpTextType": "None",
      "helpText": " ",
      "layoutType": "Field",
      "id": "67b22c79b6eb6a0500f0cfca",
      "row": 1,
      "col": 7,
      "sizex": 4,
      "sizey": 0
    }
  ],
  "fields": [
    {
      "prefix": "",
      "suffix": "",
      "placeholder": "",
      "inputType": "Telephone",
      "lengthType": "None",
      "unique": false,
      "writeOnce": false,
      "visualize": false,
      "visualizeMode": 0,
      "id": "amfso",
      "name": "Telephone",
      "key": "telephone",
      "fieldType": "Text",
      "required": false,
      "readOnly": false,
      "supportsMultipleOutputMappings": false,
      "visibleToHeroAi": false
    },
    {
      "prefix": "",
      "suffix": "",
      "placeholder": "",
      "inputType": "Email",
      "lengthType": "None",
      "unique": false,
      "writeOnce": false,
      "visualize": false,
      "visualizeMode": 0,
      "id": "ao4wj",
      "name": "Email",
      "key": "email",
      "fieldType": "Text",
      "required": false,
      "readOnly": false,
      "supportsMultipleOutputMappings": false,
      "visibleToHeroAi": false
    },
    {
      "prefix": "",
      "suffix": "",
      "placeholder": "",
      "inputType": "URL",
      "lengthType": "None",
      "unique": false,
      "writeOnce": false,
      "visualize": false,
      "visualizeMode": 0,
      "id": "af61v",
      "name": "URL",
      "key": "url",
      "fieldType": "Text",
      "required": false,
      "readOnly": false,
      "supportsMultipleOutputMappings": false,
      "visibleToHeroAi": false
    },
    {
      "supportsMultipleOutputMappings": true,
      "inputType": "Text",
      "itemLengthType": "None",
      "itemStep": 0,
      "searchPath": "aejjf._v",
      "searchPathIsArray": true,
      "searchPathCollectionExtension": "Value",
      "id": "aejjf",
      "name": "Text List",
      "key": "text-list",
      "fieldType": "List",
      "required": false,
      "readOnly": false,
      "visibleToHeroAi": false
    },
    {
      "prefix": "QAEE-",
      "id": "67b22c740f67a3dbf64ce258",
      "name": "Tracking Id",
      "description": "Tracking Id",
      "key": "tracking-id",
      "fieldType": "Tracking",
      "readOnly": true,
      "supportsMultipleOutputMappings": false,
      "visibleToHeroAi": false
    }
  ],
  "maxTrackingId": 0,
  "workspaces": [],
  "createWorkspace": false,
  "createdDate": "2025-02-16T18:20:36.522Z",
  "modifiedDate": "2025-02-16T18:20:43.839Z",
  "timeTrackingEnabled": false,
  "visibleToHeroAiEnabled": false,
  "selectionFields": {},
  "uid": "qa-e2e-kn4oi-f2bd8",
  "version": 2,
  "id": "aRp_xALtqllVSohNh",
  "name": "qa-e2e-kn4oi",
  "disabled": false
}