{"Errors":{},"Entities":{"BuilderPlaybook":[{"Acronym":null,"ApplicationId":null,"Valid":null,"Descriptor":null,"SolutionId":null,"ComponentId":null,"Uid":"qa-e2e-93nt1-32154","Version":2,"Id":"aGrDWo7bt7qobHccv","Name":"qa-e2e-93nt1","Disabled":true}],"Playbook":[{"Acronym":null,"ApplicationId":null,"Valid":null,"Descriptor":null,"SolutionId":"aGrDWo7bt7qobHccv","ComponentId":null,"Uid":"093a5835-1e23-4ce4-ab52-99185c421fac","Version":2,"Id":"67c58a5cff2d314d9cdd0434","Name":"solution_aGrDWo7bt7qobHccv_playbook","Disabled":true}]},"State":1,"Issues":{"BuilderPlaybook":[{"ErrorCode":15002,"Message":"This solution builder playbook has been disabled.","ParentId":null,"Id":"aGrDWo7bt7qobHccv","Name":"qa-e2e-93nt1"}],"Playbook":[{"ErrorCode":15000,"Message":"This playbook has been disabled.","ParentId":null,"Id":"67c58a5cff2d314d9cdd0434","Name":"solution_aGrDWo7bt7qobHccv_playbook"}]},"Images":{},"SwimlaneVersion":"25.0.5+a181fb62a23cb6088ec17cebd5ad357348154165","RelationshipGraph":null}