{"Graph":[[{"TargetIndex":1,"Direction":1},{"TargetIndex":2,"Direction":1},{"TargetIndex":3,"Direction":1}],[{"TargetIndex":0,"Direction":-1}],[{"TargetIndex":0,"Direction":-1}],[{"TargetIndex":0,"Direction":-1}]],"NodeIdToIndex":{"a6T6PLL2_knX0a6iR":0,"67c5bb7d1974dfee7f2f97ee":1,"aG_RUieVc3ba684D":2,"aU2cIwq4iVVPUXuTe":3},"IndexToNodeData":[{"NodeId":"a6T6PLL2_knX0a6iR","Type":"Application"},{"NodeId":"67c5bb7d1974dfee7f2f97ee","Type":"Report"},{"NodeId":"aG_RUieVc3ba684D","Type":"Workflow"},{"NodeId":"aU2cIwq4iVVPUXuTe","Type":"Workspace"}]}