{
  "groupBys": [],
  "aggregates": [],
  "applicationIds": [
    "aLffMYMEzpHUG3n3w"
  ],
  "columns": [
    "67b1ca219358ed5eb5c195bc"
  ],
  "sorts": {
    "67b1ca219358ed5eb5c195bc": "Ascending"
  },
  "filters": [],
  "countByApplicationFacet": false,
  "pageSize": 10,
  "offset": 0,
  "defaultSearchReport": true,
  "createdDate": "2025-02-16T11:21:05.211Z",
  "modifiedDate": "2025-02-16T11:21:12.107Z",
  "filterType": "And",
  "colorCoding": [],
  "uid": "default-f5f43",
  "version": 2,
  "id": "67b1ca219358ed5eb5c195be",
  "name": "Default",
  "disabled": false
}