{"Errors":{},"Entities":{"Application":[{"Acronym":"QAEE","ApplicationId":null,"Valid":null,"Descriptor":null,"SolutionId":null,"ComponentId":null,"Uid":"qa-e2e-buaxi-dde23","Version":2,"Id":"as7y1BlLpi3ExBFv","Name":"qa-e2e-buaxi","Disabled":false}],"Report":[{"Acronym":null,"ApplicationId":"as7y1BlLpi3ExBFv","Valid":null,"Descriptor":null,"SolutionId":null,"ComponentId":null,"Uid":"default-d17bb","Version":2,"Id":"67ab6e698f37031996554a00","Name":"Default","Disabled":false}],"Workflow":[{"Acronym":null,"ApplicationId":"as7y1BlLpi3ExBFv","Valid":null,"Descriptor":null,"SolutionId":null,"ComponentId":null,"Uid":"a4q_ZEVtfF_S5NU5r","Version":1,"Id":"a4D6H0XLGYORhl8zL","Name":null,"Disabled":false}],"Workspace":[{"Acronym":null,"ApplicationId":null,"Valid":null,"Descriptor":null,"SolutionId":null,"ComponentId":null,"Uid":"qa-e2e-buaxi-workspace-14348","Version":1,"Id":"a1Om74T9gCgblvQxn","Name":"qa-e2e-buaxi Workspace","Disabled":false}]},"State":1,"Issues":{},"Images":{},"SwimlaneVersion":"25.0.0+1b902b0fd89aeb7098875bcf7dd830906b117833","RelationshipGraph":null}