{"Errors":{},"Entities":{"Application":[{"Acronym":"QAEE","ApplicationId":null,"Valid":null,"Descriptor":null,"SolutionId":null,"ComponentId":null,"Uid":"qa-e2e-1j0fx-6d797","Version":2,"Id":"abtYYKwkMFBCsEoZI","Name":"qa-e2e-1j0fx","Disabled":false}],"Report":[{"Acronym":null,"ApplicationId":"abtYYKwkMFBCsEoZI","Valid":null,"Descriptor":null,"SolutionId":null,"ComponentId":null,"Uid":"default-8d671","Version":2,"Id":"67aeface87069857809d5a8b","Name":"Default","Disabled":false}],"Workflow":[{"Acronym":null,"ApplicationId":"abtYYKwkMFBCsEoZI","Valid":null,"Descriptor":null,"SolutionId":null,"ComponentId":null,"Uid":"aJnf3Wcui_GPvoSLk","Version":1,"Id":"aJ9lmIeMKHfPXB7EE","Name":null,"Disabled":false}],"Workspace":[{"Acronym":null,"ApplicationId":null,"Valid":null,"Descriptor":null,"SolutionId":null,"ComponentId":null,"Uid":"qa-e2e-1j0fx-workspace-cb4a6","Version":1,"Id":"aWBVxL8ppsl9KYhQi","Name":"qa-e2e-1j0fx Workspace","Disabled":false}]},"State":1,"Issues":{},"Images":{},"SwimlaneVersion":"25.0.2+9bd6cda876ba448e216db89fa56871b665d53540","RelationshipGraph":null}